[
  {
    "question": "Je mange une pomme.",
    "correctAnswer": "I am eating an apple.",
    "choices": [
      "He is eating an apple.",
      "I eat a banana.",
      "I am eating an apple.",
      "I am eating a pear.",
      "You are eating an apple."
    ]
  },
  {
    "question": "Nous allons à l’école.",
    "correctAnswer": "We are going to school.",
    "choices": [
      "We went to school.",
      "We go to the park.",
      "You are going to school.",
      "We are going to school.",
      "They are going to school."
    ]
  },
  {
    "question": "Il a un chien.",
    "correctAnswer": "He has a dog.",
    "choices": [
      "I have a dog.",
      "He is a dog.",
      "He had a dog.",
      "He has a cat.",
      "He has a dog."
    ]
  },
  {
    "question": "Tu parles français.",
    "correctAnswer": "You speak French.",
    "choices": [
      "You spoke French.",
      "You speak English.",
      "He speaks French.",
      "You speak French.",
      "You are French."
    ]
  },
  {
    "question": "Elle aime la musique.",
    "correctAnswer": "She likes music.",
    "choices": [
      "She loves books.",
      "She likes music.",
      "She hears music.",
      "She likes the movie.",
      "He likes music."
    ]
  },
  {
    "question": "Ils regardent un film.",
    "correctAnswer": "They are watching a movie.",
    "choices": [
      "They are reading a book.",
      "He is watching a movie.",
      "They are watching a show.",
      "They watched a movie.",
      "They are watching a movie."
    ]
  },
  {
    "question": "Vous avez deux frères.",
    "correctAnswer": "You have two brothers.",
    "choices": [
      "You are two brothers.",
      "They have two brothers.",
      "You have two brothers.",
      "We have two brothers.",
      "You have two sisters."
    ]
  },
  {
    "question": "Je suis fatigué.",
    "correctAnswer": "I am tired.",
    "choices": [
      "He is tired.",
      "You are tired.",
      "I am hungry.",
      "I am late.",
      "I am tired."
    ]
  },
  {
    "question": "Elle boit de l’eau.",
    "correctAnswer": "She is drinking water.",
    "choices": [
      "She drank water.",
      "He is drinking water.",
      "She is eating water.",
      "She is drinking water.",
      "She drinks wine."
    ]
  },
  {
    "question": "Nous lisons un livre.",
    "correctAnswer": "We are reading a book.",
    "choices": [
      "You are reading a book.",
      "We are writing a book.",
      "They are reading a book.",
      "We are reading a book.",
      "We read a letter."
    ]
  },
  {
    "question": "Elle aime la musique.",
    "correctAnswer": "She likes music.",
    "choices": [
      "She likes the movie.",
      "She hears music.",
      "He likes music.",
      "She likes music."
    ]
  },
  {
    "question": "Nous allons à l’école.",
    "correctAnswer": "We are going to school.",
    "choices": [
      "We go to the park.",
      "They are going to school.",
      "You are going to school.",
      "We are going to school."
    ]
  },
  {
    "question": "Nous allons à l’école.",
    "correctAnswer": "We are going to school.",
    "choices": [
      "We go to the park.",
      "They are going to school.",
      "We went to school.",
      "We are going to school."
    ]
  },
  {
    "question": "Elle boit de l’eau.",
    "correctAnswer": "She is drinking water.",
    "choices": [
      "He is drinking water.",
      "She drank water.",
      "She is eating water.",
      "She is drinking water."
    ]
  },
  {
    "question": "Vous avez deux frères.",
    "correctAnswer": "You have two brothers.",
    "choices": [
      "You are two brothers.",
      "You have two brothers.",
      "We have two brothers.",
      "You have two sisters."
    ]
  },
  {
    "question": "Ils regardent un film.",
    "correctAnswer": "They are watching a movie.",
    "choices": [
      "They are reading a book.",
      "They are watching a movie.",
      "He is watching a movie.",
      "They are watching a show."
    ]
  },
  {
    "question": "Je suis fatigué.",
    "correctAnswer": "I am tired.",
    "choices": [
      "I am tired.",
      "He is tired.",
      "I am hungry.",
      "You are tired."
    ]
  },
  {
    "question": "Tu parles français.",
    "correctAnswer": "You speak French.",
    "choices": [
      "You speak French.",
      "You spoke French.",
      "He speaks French.",
      "You speak English."
    ]
  },
  {
    "question": "Nous lisons un livre.",
    "correctAnswer": "We are reading a book.",
    "choices": [
      "You are reading a book.",
      "We are reading a book.",
      "We are writing a book.",
      "We read a letter."
    ]
  },
  {
    "question": "Nous allons à l’école.",
    "correctAnswer": "We are going to school.",
    "choices": [
      "We are going to school.",
      "We went to school.",
      "They are going to school.",
      "We go to the park."
    ]
  },
  {
    "question": "Nous lisons un livre.",
    "correctAnswer": "We are reading a book.",
    "choices": [
      "We are writing a book.",
      "They are reading a book.",
      "We are reading a book.",
      "We read a letter."
    ]
  },
  {
    "question": "Elle boit de l’eau.",
    "correctAnswer": "She is drinking water.",
    "choices": [
      "He is drinking water.",
      "She drank water.",
      "She is drinking water.",
      "She drinks wine."
    ]
  },
  {
    "question": "Nous allons à l’école.",
    "correctAnswer": "We are going to school.",
    "choices": [
      "They are going to school.",
      "We are going to school.",
      "You are going to school.",
      "We go to the park."
    ]
  },
  {
    "question": "Nous lisons un livre.",
    "correctAnswer": "We are reading a book.",
    "choices": [
      "You are reading a book.",
      "We are writing a book.",
      "They are reading a book.",
      "We are reading a book."
    ]
  },
  {
    "question": "Elle boit de l’eau.",
    "correctAnswer": "She is drinking water.",
    "choices": [
      "She drank water.",
      "She drinks wine.",
      "He is drinking water.",
      "She is drinking water."
    ]
  },
  {
    "question": "Nous allons à l’école.",
    "correctAnswer": "We are going to school.",
    "choices": [
      "We are going to school.",
      "We went to school.",
      "They are going to school.",
      "You are going to school."
    ]
  },
  {
    "question": "Vous avez deux frères.",
    "correctAnswer": "You have two brothers.",
    "choices": [
      "You have two brothers.",
      "We have two brothers.",
      "They have two brothers.",
      "You have two sisters."
    ]
  },
  {
    "question": "Vous avez deux frères.",
    "correctAnswer": "You have two brothers.",
    "choices": [
      "You have two sisters.",
      "You have two brothers.",
      "They have two brothers.",
      "We have two brothers."
    ]
  },
  {
    "question": "Vous avez deux frères.",
    "correctAnswer": "You have two brothers.",
    "choices": [
      "You are two brothers.",
      "You have two brothers.",
      "They have two brothers.",
      "You have two sisters."
    ]
  },
  {
    "question": "Je mange une pomme.",
    "correctAnswer": "I am eating an apple.",
    "choices": [
      "You are eating an apple.",
      "He is eating an apple.",
      "I am eating an apple.",
      "I eat a banana."
    ]
  },
  {
    "question": "Tu parles français.",
    "correctAnswer": "You speak French.",
    "choices": [
      "He speaks French.",
      "You speak English.",
      "You spoke French.",
      "You speak French."
    ]
  },
  {
    "question": "Ils regardent un film.",
    "correctAnswer": "They are watching a movie.",
    "choices": [
      "They are watching a movie.",
      "They are watching a show.",
      "They watched a movie.",
      "They are reading a book."
    ]
  },
  {
    "question": "Je suis fatigué.",
    "correctAnswer": "I am tired.",
    "choices": [
      "I am late.",
      "I am tired.",
      "I am hungry.",
      "He is tired."
    ]
  },
  {
    "question": "Ils regardent un film.",
    "correctAnswer": "They are watching a movie.",
    "choices": [
      "They watched a movie.",
      "They are watching a movie.",
      "They are reading a book.",
      "They are watching a show."
    ]
  },
  {
    "question": "Nous lisons un livre.",
    "correctAnswer": "We are reading a book.",
    "choices": [
      "We are writing a book.",
      "You are reading a book.",
      "We are reading a book.",
      "We read a letter."
    ]
  },
  {
    "question": "Vous avez deux frères.",
    "correctAnswer": "You have two brothers.",
    "choices": [
      "We have two brothers.",
      "You have two brothers.",
      "You are two brothers.",
      "You have two sisters."
    ]
  },
  {
    "question": "Nous lisons un livre.",
    "correctAnswer": "We are reading a book.",
    "choices": [
      "We are writing a book.",
      "We are reading a book.",
      "They are reading a book.",
      "We read a letter."
    ]
  },
  {
    "question": "Je mange une pomme.",
    "correctAnswer": "I am eating an apple.",
    "choices": [
      "You are eating an apple.",
      "He is eating an apple.",
      "I eat a banana.",
      "I am eating an apple."
    ]
  },
  {
    "question": "Elle aime la musique.",
    "correctAnswer": "She likes music.",
    "choices": [
      "She likes music.",
      "She loves books.",
      "He likes music.",
      "She likes the movie."
    ]
  },
  {
    "question": "Nous allons à l’école.",
    "correctAnswer": "We are going to school.",
    "choices": [
      "We go to the park.",
      "You are going to school.",
      "They are going to school.",
      "We are going to school."
    ]
  },
  {
    "question": "Elle aime la musique.",
    "correctAnswer": "She likes music.",
    "choices": [
      "She loves books.",
      "He likes music.",
      "She likes the movie.",
      "She likes music."
    ]
  },
  {
    "question": "Tu parles français.",
    "correctAnswer": "You speak French.",
    "choices": [
      "You speak English.",
      "You speak French.",
      "You spoke French.",
      "He speaks French."
    ]
  },
  {
    "question": "Nous allons à l’école.",
    "correctAnswer": "We are going to school.",
    "choices": [
      "We are going to school.",
      "You are going to school.",
      "They are going to school.",
      "We went to school."
    ]
  },
  {
    "question": "Nous lisons un livre.",
    "correctAnswer": "We are reading a book.",
    "choices": [
      "We read a letter.",
      "We are writing a book.",
      "You are reading a book.",
      "We are reading a book."
    ]
  },
  {
    "question": "Je suis fatigué.",
    "correctAnswer": "I am tired.",
    "choices": [
      "You are tired.",
      "He is tired.",
      "I am tired.",
      "I am hungry."
    ]
  },
  {
    "question": "Nous allons à l’école.",
    "correctAnswer": "We are going to school.",
    "choices": [
      "You are going to school.",
      "We went to school.",
      "We go to the park.",
      "We are going to school."
    ]
  },
  {
    "question": "Nous lisons un livre.",
    "correctAnswer": "We are reading a book.",
    "choices": [
      "They are reading a book.",
      "We read a letter.",
      "You are reading a book.",
      "We are reading a book."
    ]
  },
  {
    "question": "Nous allons à l’école.",
    "correctAnswer": "We are going to school.",
    "choices": [
      "They are going to school.",
      "We are going to school.",
      "You are going to school.",
      "We went to school."
    ]
  },
  {
    "question": "Je suis fatigué.",
    "correctAnswer": "I am tired.",
    "choices": [
      "I am late.",
      "I am hungry.",
      "He is tired.",
      "I am tired."
    ]
  },
  {
    "question": "Nous allons à l’école.",
    "correctAnswer": "We are going to school.",
    "choices": [
      "You are going to school.",
      "We went to school.",
      "We are going to school.",
      "We go to the park."
    ]
  },
  {
    "question": "Tu parles français.",
    "correctAnswer": "You speak French.",
    "choices": [
      "He speaks French.",
      "You spoke French.",
      "You are French.",
      "You speak French."
    ]
  },
  {
    "question": "Je suis fatigué.",
    "correctAnswer": "I am tired.",
    "choices": [
      "I am tired.",
      "I am hungry.",
      "I am late.",
      "He is tired."
    ]
  },
  {
    "question": "Vous avez deux frères.",
    "correctAnswer": "You have two brothers.",
    "choices": [
      "They have two brothers.",
      "We have two brothers.",
      "You have two brothers.",
      "You are two brothers."
    ]
  },
  {
    "question": "Je suis fatigué.",
    "correctAnswer": "I am tired.",
    "choices": [
      "I am hungry.",
      "I am tired.",
      "I am late.",
      "He is tired."
    ]
  },
  {
    "question": "Elle boit de l’eau.",
    "correctAnswer": "She is drinking water.",
    "choices": [
      "She drinks wine.",
      "She drank water.",
      "She is eating water.",
      "She is drinking water."
    ]
  },
  {
    "question": "Nous lisons un livre.",
    "correctAnswer": "We are reading a book.",
    "choices": [
      "We are reading a book.",
      "They are reading a book.",
      "We are writing a book.",
      "We read a letter."
    ]
  },
  {
    "question": "Elle aime la musique.",
    "correctAnswer": "She likes music.",
    "choices": [
      "She likes music.",
      "He likes music.",
      "She likes the movie.",
      "She hears music."
    ]
  },
  {
    "question": "Je suis fatigué.",
    "correctAnswer": "I am tired.",
    "choices": [
      "I am hungry.",
      "He is tired.",
      "I am tired.",
      "I am late."
    ]
  },
  {
    "question": "Ils regardent un film.",
    "correctAnswer": "They are watching a movie.",
    "choices": [
      "They are watching a movie.",
      "He is watching a movie.",
      "They watched a movie.",
      "They are reading a book."
    ]
  },
  {
    "question": "Je mange une pomme.",
    "correctAnswer": "I am eating an apple.",
    "choices": [
      "I am eating an apple.",
      "I am eating a pear.",
      "You are eating an apple.",
      "He is eating an apple."
    ]
  },
  {
    "question": "Je mange une pomme.",
    "correctAnswer": "I am eating an apple.",
    "choices": [
      "I am eating a pear.",
      "You are eating an apple.",
      "I am eating an apple.",
      "He is eating an apple."
    ]
  },
  {
    "question": "Je mange une pomme.",
    "correctAnswer": "I am eating an apple.",
    "choices": [
      "I am eating a pear.",
      "He is eating an apple.",
      "You are eating an apple.",
      "I am eating an apple."
    ]
  },
  {
    "question": "Il a un chien.",
    "correctAnswer": "He has a dog.",
    "choices": [
      "He has a dog.",
      "He has a cat.",
      "He is a dog.",
      "He had a dog."
    ]
  },
  {
    "question": "Vous avez deux frères.",
    "correctAnswer": "You have two brothers.",
    "choices": [
      "We have two brothers.",
      "You are two brothers.",
      "You have two sisters.",
      "You have two brothers."
    ]
  },
  {
    "question": "Vous avez deux frères.",
    "correctAnswer": "You have two brothers.",
    "choices": [
      "They have two brothers.",
      "You are two brothers.",
      "You have two brothers.",
      "You have two sisters."
    ]
  },
  {
    "question": "Vous avez deux frères.",
    "correctAnswer": "You have two brothers.",
    "choices": [
      "You are two brothers.",
      "You have two brothers.",
      "We have two brothers.",
      "They have two brothers."
    ]
  },
  {
    "question": "Il a un chien.",
    "correctAnswer": "He has a dog.",
    "choices": [
      "I have a dog.",
      "He has a dog.",
      "He is a dog.",
      "He had a dog."
    ]
  },
  {
    "question": "Je suis fatigué.",
    "correctAnswer": "I am tired.",
    "choices": [
      "I am tired.",
      "You are tired.",
      "I am late.",
      "He is tired."
    ]
  },
  {
    "question": "Elle boit de l’eau.",
    "correctAnswer": "She is drinking water.",
    "choices": [
      "She is drinking water.",
      "He is drinking water.",
      "She is eating water.",
      "She drinks wine."
    ]
  },
  {
    "question": "Nous lisons un livre.",
    "correctAnswer": "We are reading a book.",
    "choices": [
      "We are reading a book.",
      "We are writing a book.",
      "You are reading a book.",
      "We read a letter."
    ]
  },
  {
    "question": "Ils regardent un film.",
    "correctAnswer": "They are watching a movie.",
    "choices": [
      "They are watching a movie.",
      "They are watching a show.",
      "They are reading a book.",
      "They watched a movie."
    ]
  },
  {
    "question": "Ils regardent un film.",
    "correctAnswer": "They are watching a movie.",
    "choices": [
      "They are reading a book.",
      "They are watching a movie.",
      "They are watching a show.",
      "They watched a movie."
    ]
  },
  {
    "question": "Il a un chien.",
    "correctAnswer": "He has a dog.",
    "choices": [
      "I have a dog.",
      "He had a dog.",
      "He has a dog.",
      "He is a dog."
    ]
  },
  {
    "question": "Nous lisons un livre.",
    "correctAnswer": "We are reading a book.",
    "choices": [
      "You are reading a book.",
      "We are reading a book.",
      "We read a letter.",
      "They are reading a book."
    ]
  },
  {
    "question": "Elle boit de l’eau.",
    "correctAnswer": "She is drinking water.",
    "choices": [
      "She is drinking water.",
      "He is drinking water.",
      "She drank water.",
      "She drinks wine."
    ]
  },
  {
    "question": "Je mange une pomme.",
    "correctAnswer": "I am eating an apple.",
    "choices": [
      "I am eating an apple.",
      "I eat a banana.",
      "He is eating an apple.",
      "I am eating a pear."
    ]
  },
  {
    "question": "Ils regardent un film.",
    "correctAnswer": "They are watching a movie.",
    "choices": [
      "He is watching a movie.",
      "They are watching a movie.",
      "They watched a movie.",
      "They are reading a book."
    ]
  },
  {
    "question": "Nous lisons un livre.",
    "correctAnswer": "We are reading a book.",
    "choices": [
      "They are reading a book.",
      "We are writing a book.",
      "We are reading a book.",
      "You are reading a book."
    ]
  },
  {
    "question": "Nous lisons un livre.",
    "correctAnswer": "We are reading a book.",
    "choices": [
      "We are reading a book.",
      "They are reading a book.",
      "You are reading a book.",
      "We read a letter."
    ]
  },
  {
    "question": "Tu parles français.",
    "correctAnswer": "You speak French.",
    "choices": [
      "You are French.",
      "You speak French.",
      "You spoke French.",
      "He speaks French."
    ]
  },
  {
    "question": "Elle boit de l’eau.",
    "correctAnswer": "She is drinking water.",
    "choices": [
      "She drinks wine.",
      "She drank water.",
      "She is eating water.",
      "She is drinking water."
    ]
  },
  {
    "question": "Je suis fatigué.",
    "correctAnswer": "I am tired.",
    "choices": [
      "I am late.",
      "He is tired.",
      "I am tired.",
      "I am hungry."
    ]
  },
  {
    "question": "Elle boit de l’eau.",
    "correctAnswer": "She is drinking water.",
    "choices": [
      "She is drinking water.",
      "He is drinking water.",
      "She is eating water.",
      "She drinks wine."
    ]
  },
  {
    "question": "Je mange une pomme.",
    "correctAnswer": "I am eating an apple.",
    "choices": [
      "I am eating a pear.",
      "I am eating an apple.",
      "He is eating an apple.",
      "I eat a banana."
    ]
  },
  {
    "question": "Elle boit de l’eau.",
    "correctAnswer": "She is drinking water.",
    "choices": [
      "She drinks wine.",
      "She drank water.",
      "She is drinking water.",
      "He is drinking water."
    ]
  },
  {
    "question": "Je mange une pomme.",
    "correctAnswer": "I am eating an apple.",
    "choices": [
      "I am eating an apple.",
      "He is eating an apple.",
      "You are eating an apple.",
      "I am eating a pear."
    ]
  },
  {
    "question": "Je suis fatigué.",
    "correctAnswer": "I am tired.",
    "choices": [
      "I am late.",
      "You are tired.",
      "He is tired.",
      "I am tired."
    ]
  },
  {
    "question": "Vous avez deux frères.",
    "correctAnswer": "You have two brothers.",
    "choices": [
      "They have two brothers.",
      "We have two brothers.",
      "You have two sisters.",
      "You have two brothers."
    ]
  },
  {
    "question": "Je suis fatigué.",
    "correctAnswer": "I am tired.",
    "choices": [
      "I am late.",
      "I am tired.",
      "He is tired.",
      "I am hungry."
    ]
  },
  {
    "question": "Il a un chien.",
    "correctAnswer": "He has a dog.",
    "choices": [
      "He had a dog.",
      "I have a dog.",
      "He has a dog.",
      "He is a dog."
    ]
  },
  {
    "question": "Vous avez deux frères.",
    "correctAnswer": "You have two brothers.",
    "choices": [
      "You are two brothers.",
      "You have two sisters.",
      "You have two brothers.",
      "We have two brothers."
    ]
  },
  {
    "question": "Je mange une pomme.",
    "correctAnswer": "I am eating an apple.",
    "choices": [
      "I am eating a pear.",
      "I eat a banana.",
      "You are eating an apple.",
      "I am eating an apple."
    ]
  },
  {
    "question": "Il a un chien.",
    "correctAnswer": "He has a dog.",
    "choices": [
      "He is a dog.",
      "I have a dog.",
      "He has a dog.",
      "He has a cat."
    ]
  },
  {
    "question": "Ils regardent un film.",
    "correctAnswer": "They are watching a movie.",
    "choices": [
      "He is watching a movie.",
      "They are watching a movie.",
      "They are reading a book.",
      "They watched a movie."
    ]
  },
  {
    "question": "Ils regardent un film.",
    "correctAnswer": "They are watching a movie.",
    "choices": [
      "He is watching a movie.",
      "They watched a movie.",
      "They are watching a movie.",
      "They are watching a show."
    ]
  },
  {
    "question": "Je mange une pomme.",
    "correctAnswer": "I am eating an apple.",
    "choices": [
      "I am eating an apple.",
      "You are eating an apple.",
      "I am eating a pear.",
      "I eat a banana."
    ]
  },
  {
    "question": "Je suis fatigué.",
    "correctAnswer": "I am tired.",
    "choices": [
      "He is tired.",
      "I am late.",
      "I am tired.",
      "You are tired."
    ]
  },
  {
    "question": "Je mange une pomme.",
    "correctAnswer": "I am eating an apple.",
    "choices": [
      "He is eating an apple.",
      "I am eating an apple.",
      "I eat a banana.",
      "I am eating a pear."
    ]
  },
  {
    "question": "Tu parles français.",
    "correctAnswer": "You speak French.",
    "choices": [
      "You are French.",
      "You speak French.",
      "You spoke French.",
      "You speak English."
    ]
  },
  {
    "question": "Nous allons à l’école.",
    "correctAnswer": "We are going to school.",
    "choices": [
      "They are going to school.",
      "You are going to school.",
      "We go to the park.",
      "We are going to school."
    ]
  }
]